shp2postgis/Data2Sql.py
shp2postgis/Shp2Postgis.py
shp2postgis/Util.py
shp2postgis/__init__.py
shp2postgis/__main__.py
shp2postgis-0.3.1.dist-info/LICENSE.txt
shp2postgis-0.3.1.dist-info/METADATA
shp2postgis-0.3.1.dist-info/WHEEL
shp2postgis-0.3.1.dist-info/top_level.txt
shp2postgis-0.3.1.dist-info/RECORD
