Metadata-Version: 2.1
Name: shp2postgis
Version: 0.3.1
Summary: shapefile to sql converter.
Home-page: https://github.com/johnyjpsf/shp2postgis
Author: Johny Patrick da Silva Ferreira
Author-email: johnypatrick5@gmail.com
License: MIT
Keywords: gis geospatial geographic shapefile shapefiles postgis postgre sql database
Platform: UNKNOWN
Classifier: Programming Language :: Python :: 3
Classifier: License :: OSI Approved :: MIT License
Classifier: Operating System :: OS Independent
Classifier: Topic :: Scientific/Engineering :: GIS
Classifier: Topic :: Software Development :: Libraries
Classifier: Topic :: Software Development :: Libraries :: Python Modules
Requires-Python: >=3.6
